ayto/__init__.py
ayto/ayto.py
ayto/utils.py
ayto-1.0.1.dist-info/LICENSE
ayto-1.0.1.dist-info/METADATA
ayto-1.0.1.dist-info/WHEEL
ayto-1.0.1.dist-info/top_level.txt
ayto-1.0.1.dist-info/RECORD
