Metadata-Version: 2.1
Name: ayto
Version: 1.0.1
Summary: A Python library for calculating couple probabilites for the TV show *Are You the One?*
Author-email: Dan Turkel <daturkel@gmail.com>
Project-URL: Homepage, https://github.com/daturkel/ayto
Project-URL: Bug Tracker, https://github.com/daturkel/ayto/issues
Project-URL: Author's Website, https://danturkel.com
Classifier: Programming Language :: Python :: 3
Classifier: Programming Language :: Python :: 3.8
Classifier: Programming Language :: Python :: 3.9
Classifier: Programming Language :: Python :: 3.10
Classifier: Programming Language :: Python :: 3.11
Classifier: License :: OSI Approved :: MIT License
Classifier: Operating System :: OS Independent
Requires-Python: >=3.7
License-File: LICENSE
Requires-Dist: numpy
Requires-Dist: pandas
Provides-Extra: dev
Requires-Dist: mypy (>=0.991) ; extra == 'dev'
Requires-Dist: pytest (>=7.2) ; extra == 'dev'
Requires-Dist: pytest-benchmark (>=4.0) ; extra == 'dev'
Requires-Dist: pytest-cov (>=4.0) ; extra == 'dev'
